Workbook

Sheet ReadMe
A1: Workbook | B1: D365 Advanced Practice Dataset
A2: Purpose | B2: Training dataset for D365 F&O Technical, Finance Functional, and SCM Functional hands-on labs
A3: Coverage | B3: Products, inventory structure, customers, vendors, purchase orders, sales orders, transfers, GL journals, payments, order tracking, and scenarios
A4: Suggested Use | B4: Use master data sheets first, then execute transactions and scenarios module by module
A5: Key Notes | B5: Line totals in transaction sheets are formula-driven; scenario sheet maps sample exercises
A6: Record Volume | B6: 100+ records across sheets for practice, import, reporting, and troubleshooting

Sheet Products
A1: ItemId | B1: Name | C1: ItemGroup | D1: ProductType | E1: CostPrice | F1: SalesPrice | G1: Unit | H1: Site | I1: Warehouse | J1: Status
A2: ITEM001 | B2: Laptop Basic | C2: ITHW | D2: Item | E2: 500 | F2: 650.05 | G2: box | H2: S1 | I2: WH1 | J2: Active
A3: ITEM002 | B3: Laptop Pro | C3: ELEC | D3: Item | E3: 45 | F3: 59.08 | G3: ea | H3: S1 | I3: WH3 | J3: Active
A4: ITEM003 | B4: Wireless Mouse | C4: ELEC | D4: Item | E4: 120 | F4: 151.72 | G4: ea | H4: S1 | I4: WH1 | J4: Active
A5: ITEM004 | B5: Keyboard Standard | C5: ITHW | D5: Item | E5: 250 | F5: 380.23 | G5: ea | H5: S1 | I5: WH3 | J5: Active
A6: ITEM005 | B6: Monitor 24 | C6: OFFICE | D6: Item | E6: 500 | F6: 782.8 | G6: ea | H6: S1 | I6: WH2 | J6: Active
A7: ITEM006 | B7: Monitor 27 | C7: ELEC | D7: Item | E7: 320 | F7: 440.06 | G7: ea | H7: S1 | I7: WH3 | J7: Active
A8: ITEM007 | B8: Docking Station | C8: ELEC | D8: Item | E8: 120 | F8: 168.37 | G8: ea | H8: S1 | I8: WH2 | J8: Active
A9: ITEM008 | B9: USB-C Cable | C9: ELEC | D9: Item | E9: 20 | F9: 25.83 | G9: box | H9: S1 | I9: WH2 | J9: Active
A10: ITEM009 | B10: Headset Pro | C10: ELEC | D10: Item | E10: 320 | F10: 438.09 | G10: box | H10: S1 | I10: WH3 | J10: Active
A11: ITEM010 | B11: Webcam HD | C11: OFFICE | D11: Item | E11: 20 | F11: 33.76 | G11: ea | H11: S1 | I11: WH3 | J11: Active
A12: ITEM011 | B12: Office Chair | C12: ITHW | D12: Item | E12: 60 | F12: 97.39 | G12: box | H12: S1 | I12: WH3 | J12: Active
A13: ITEM012 | B13: Desk Adjustable | C13: ELEC | D13: Item | E13: 45 | F13: 70.52 | G13: ea | H13: S1 | I13: WH2 | J13: Active
... A26: ITEM025 | B26: Label Printer | C26: ELEC | D26: Item | E26: 900 | F26: 1144.08 | G26: ea | H26: S1 | I26: WH3 | J26: Active

Sheet InventoryStructure
A1: Site | B1: Warehouse | C1: Location | D1: WarehouseType | E1: DefaultReceipt | F1: DefaultIssue | G1: Status
A2: S1 | B2: WH1 | C2: WH1-L01 | D2: Standard | E2: Yes | F2: No | G2: Active
A3: S1 | B3: WH1 | C3: WH1-L02 | D3: Pick | E3: No | F3: Yes | G3: Active
A4: S1 | B4: WH1 | C4: WH1-L03 | D4: Bulk | E4: No | F4: No | G4: Active
A5: S1 | B5: WH1 | C5: WH1-L04 | D5: Pick | E5: No | F5: No | G5: Active
A6: S1 | B6: WH1 | C6: WH1-L05 | D6: Standard | E6: No | F6: No | G6: Active
A7: S1 | B7: WH2 | C7: WH2-L01 | D7: Bulk | E7: Yes | F7: No | G7: Active
A8: S1 | B8: WH2 | C8: WH2-L02 | D8: Bulk | E8: No | F8: Yes | G8: Active
A9: S1 | B9: WH2 | C9: WH2-L03 | D9: Pick | E9: No | F9: No | G9: Active
A10: S1 | B10: WH2 | C10: WH2-L04 | D10: Bulk | E10: No | F10: No | G10: Active
A11: S1 | B11: WH2 | C11: WH2-L05 | D11: Pick | E11: No | F11: No | G11: Active
A12: S1 | B12: WH3 | C12: WH3-L01 | D12: Bulk | E12: Yes | F12: No | G12: Active
... A16: S1 | B16: WH3 | C16: WH3-L05 | D16: Pick | E16: No | F16: No | G16: Active

Sheet Customers
A1: CustomerId | B1: Name | C1: CustomerGroup | D1: CreditLimit | E1: Currency | F1: PaymentTerms | G1: City | H1: State | I1: Status
A2: CUST001 | B2: ABC Retail | C2: B2B | D2: 15000 | E2: USD | F2: Net 30 | G2: Austin | H2: TX | I2: Active
A3: CUST002 | B3: XYZ Stores | C3: WHOLESALE | D3: 8000 | E3: USD | F3: Net 15 | G3: Seattle | H3: WA | I3: Active
A4: CUST003 | B4: Northwind Traders | C4: RETAIL | D4: 10000 | E4: USD | F4: Net 15 | G4: Chicago | H4: IL | I4: Active
A5: CUST004 | B5: Contoso Sales | C5: RETAIL | D5: 3000 | E5: USD | F5: Net 45 | G5: Denver | H5: CO | I5: Active
A6: CUST005 | B6: Fabrikam Distribution | C6: WHOLESALE | D6: 8000 | E6: USD | F6: Net 45 | G6: Phoenix | H6: AZ | I6: Active
A7: CUST006 | B7: Blue Ocean Market | C7: B2B | D7: 15000 | E7: USD | F7: Net 15 | G7: Atlanta | H7: GA | I7: Active
A8: CUST007 | B8: Summit Office | C8: WHOLESALE | D8: 8000 | E8: USD | F8: Net 45 | G8: Boston | H8: MA | I8: Active
A9: CUST008 | B9: Brightline Tech | C9: WHOLESALE | D9: 15000 | E9: USD | F9: Net 15 | G9: Dallas | H9: TX | I9: Active
A10: CUST009 | B10: Urban Supply | C10: B2B | D10: 8000 | E10: USD | F10: Net 15 | G10: Miami | H10: FL | I10: Active
A11: CUST010 | B11: Prime Electronics | C11: WHOLESALE | D11: 15000 | E11: USD | F11: Net 15 | G11: San Jose | H11: CA | I11: Active
A12: CUST011 | B12: Vista Wholesale | C12: WHOLESALE | D12: 8000 | E12: USD | F12: Net 30 | G12: Austin | H12: TX | I12: Active
A13: CUST012 | B13: Central Retailers | C13: B2B | D13: 3000 | E13: USD | F13: Net 30 | G13: Seattle | H13: WA | I13: Active
... A21: CUST020 | B21: Orbit Retail | C21: WHOLESALE | D21: 5000 | E21: USD | F21: Net 45 | G21: San Jose | H21: CA | I21: Active

Sheet Vendors
A1: VendorId | B1: Name | C1: VendorGroup | D1: Currency | E1: PaymentTerms | F1: City | G1: State | H1: Status
A2: VEND001 | B2: Tech Supplier | C2: IMPORT | D2: USD | E2: Net 30 | F2: Denver | G2: CO | H2: Active
A3: VEND002 | B3: Office Supplies Co | C3: SERV | D3: USD | E3: Net 60 | F3: Phoenix | G3: AZ | H3: Active
A4: VEND003 | B4: Global Components | C4: IMPORT | D4: USD | E4: Net 30 | F4: Atlanta | G4: GA | H4: Active
A5: VEND004 | B5: Northstar Hardware | C5: SERV | D5: USD | E5: Net 30 | F5: Boston | G5: MA | H5: Active
A6: VEND005 | B6: Summit Imports | C6: LOCAL | D6: USD | E6: Net 15 | F6: Dallas | G6: TX | H6: Active
A7: VEND006 | B7: Prime Parts | C7: LOCAL | D7: USD | E7: Net 15 | F7: Miami | G7: FL | H7: Active
A8: VEND007 | B8: LogiSource | C8: IMPORT | D8: USD | E8: Net 15 | F8: San Jose | G8: CA | H8: Active
A9: VEND008 | B9: Alpha Devices | C9: SERV | D9: USD | E9: Net 60 | F9: Austin | G9: TX | H9: Active
A10: VEND009 | B10: Nexus Distribution | C10: LOCAL | D10: USD | E10: Net 60 | F10: Seattle | G10: WA | H10: Active
A11: VEND010 | B11: Evergreen Office | C11: LOCAL | D11: USD | E11: Net 15 | F11: Chicago | G11: IL | H11: Active
A12: VEND011 | B12: Pioneer Systems | C12: LOCAL | D12: USD | E12: Net 60 | F12: Denver | G12: CO | H12: Active
... A16: VEND015 | B16: Apex Sourcing | C16: LOCAL | D16: USD | E16: Net 60 | F16: Dallas | G16: TX | H16: Active

Sheet PurchaseOrders
A1: POId | B1: OrderDate | C1: VendorId | D1: ItemId | E1: Qty | F1: UnitCost | G1: LineAmount | H1: Warehouse | I1: ReceiptStatus | J1: InvoiceStatus
A2: PO0001 | B2: 46026 | C2: VEND011 | D2: ITEM008 | E2: 10 | F2: 20 | G2: =E2*F2 -> 200 | H2: WH2 | I2: Received | J2: Pending
A3: PO0002 | B3: 46027 | C3: VEND004 | D3: ITEM005 | E3: 20 | F3: 500 | G3: =E3*F3 -> 10000 | H3: WH2 | I3: Partially Received | J3: Invoiced
A4: PO0003 | B4: 46028 | C4: VEND011 | D4: ITEM004 | E4: 3 | F4: 250 | G4: =E4*F4 -> 750 | H4: WH2 | I4: Partially Received | J4: Pending
A5: PO0004 | B5: 46029 | C5: VEND014 | D5: ITEM014 | E5: 20 | F5: 180 | G5: =E5*F5 -> 3600 | H5: WH3 | I5: Received | J5: Pending
A6: PO0005 | B6: 46030 | C6: VEND001 | D6: ITEM021 | E6: 3 | F6: 180 | G6: =E6*F6 -> 540 | H6: WH2 | I6: Open | J6: Pending
A7: PO0006 | B7: 46031 | C7: VEND004 | D7: ITEM004 | E7: 8 | F7: 250 | G7: =E7*F7 -> 2000 | H7: WH1 | I7: Open | J7: Pending
A8: PO0007 | B8: 46032 | C8: VEND003 | D8: ITEM005 | E8: 15 | F8: 500 | G8: =E8*F8 -> 7500 | H8: WH2 | I8: Partially Received | J8: Invoiced
A9: PO0008 | B9: 46033 | C9: VEND013 | D9: ITEM003 | E9: 20 | F9: 120 | G9: =E9*F9 -> 2400 | H9: WH3 | I9: Received | J9: Invoiced
A10: PO0009 | B10: 46034 | C10: VEND002 | D10: ITEM021 | E10: 2 | F10: 180 | G10: =E10*F10 -> 360 | H10: WH1 | I10: Received | J10: Pending
A11: PO0010 | B11: 46035 | C11: VEND004 | D11: ITEM016 | E11: 20 | F11: 500 | G11: =E11*F11 -> 10000 | H11: WH2 | I11: Received | J11: Invoiced
A12: PO0011 | B12: 46036 | C12: VEND007 | D12: ITEM013 | E12: 2 | F12: 20 | G12: =E12*F12 -> 40 | H12: WH2 | I12: Partially Received | J12: Pending
A13: PO0012 | B13: 46037 | C13: VEND003 | D13: ITEM014 | E13: 20 | F13: 180 | G13: =E13*F13 -> 3600 | H13: WH1 | I13: Partially Received | J13: Invoiced
... A46: PO0045 | B46: 46070 | C46: VEND007 | D46: ITEM012 | E46: 12 | F46: 45 | G46: =E46*F46 -> 540 | H46: WH3 | I46: Open | J46: Invoiced

Sheet SalesOrders
A1: SOId | B1: OrderDate | C1: CustomerId | D1: ItemId | E1: Qty | F1: UnitPrice | G1: LineAmount | H1: Warehouse | I1: ShipmentStatus | J1: InvoiceStatus
A2: SO0001 | B2: 46031 | C2: CUST007 | D2: ITEM013 | E2: 5 | F2: 32.7 | G2: =E2*F2 -> 163.5 | H2: WH2 | I2: Shipped | J2: Pending
A3: SO0002 | B3: 46032 | C3: CUST017 | D3: ITEM014 | E3: 1 | F3: 276.49 | G3: =E3*F3 -> 276.49 | H3: WH3 | I3: Open | J3: Pending
A4: SO0003 | B4: 46033 | C4: CUST007 | D4: ITEM024 | E4: 6 | F4: 76.45 | G4: =E4*F4 -> 458.7 | H4: WH2 | I4: Packed | J4: Invoiced
A5: SO0004 | B5: 46034 | C5: CUST020 | D5: ITEM022 | E5: 3 | F5: 78.77 | G5: =E5*F5 -> 236.31 | H5: WH2 | I5: Open | J5: Invoiced
A6: SO0005 | B6: 46035 | C6: CUST017 | D6: ITEM024 | E6: 3 | F6: 76.45 | G6: =E6*F6 -> 229.35 | H6: WH2 | I6: Open | J6: Pending
A7: SO0006 | B7: 46036 | C7: CUST010 | D7: ITEM011 | E7: 4 | F7: 97.39 | G7: =E7*F7 -> 389.56 | H7: WH3 | I7: Shipped | J7: Invoiced
A8: SO0007 | B8: 46037 | C8: CUST013 | D8: ITEM014 | E8: 6 | F8: 276.49 | G8: =E8*F8 -> 1658.94 | H8: WH3 | I8: Open | J8: Invoiced
A9: SO0008 | B9: 46038 | C9: CUST010 | D9: ITEM020 | E9: 5 | F9: 526.2 | G9: =E9*F9 -> 2631 | H9: WH2 | I9: Open | J9: Invoiced
A10: SO0009 | B10: 46039 | C10: CUST007 | D10: ITEM010 | E10: 3 | F10: 33.76 | G10: =E10*F10 -> 101.28 | H10: WH2 | I10: Open | J10: Pending
A11: SO0010 | B11: 46040 | C11: CUST015 | D11: ITEM021 | E11: 3 | F11: 257.05 | G11: =E11*F11 -> 771.15 | H11: WH2 | I11: Packed | J11: Pending
A12: SO0011 | B12: 46041 | C12: CUST016 | D12: ITEM007 | E12: 5 | F12: 168.37 | G12: =E12*F12 -> 841.85 | H12: WH3 | I12: Shipped | J12: Pending
A13: SO0012 | B13: 46042 | C13: CUST017 | D13: ITEM003 | E13: 3 | F13: 151.72 | G13: =E13*F13 -> 455.16 | H13: WH3 | I13: Open | J13: Pending
... A61: SO0060 | B61: 46090 | C61: CUST008 | D61: ITEM018 | E61: 8 | F61: 138.49 | G61: =E61*F61 -> 1107.92 | H61: WH3 | I61: Packed | J61: Pending

Sheet InventoryTransfers
A1: TransferId | B1: TransferDate | C1: ItemId | D1: Qty | E1: FromWarehouse | F1: FromLocation | G1: ToWarehouse | H1: ToLocation | I1: Status
A2: TR0001 | B2: 46036 | C2: ITEM003 | D2: 3 | E2: WH3 | F2: WH3-L04 | G2: WH2 | H2: WH2-L01 | I2: Transferred
A3: TR0002 | B3: 46037 | C3: ITEM012 | D3: 5 | E3: WH2 | F3: WH2-L03 | G3: WH1 | H3: WH1-L05 | I3: Open
A4: TR0003 | B4: 46038 | C4: ITEM011 | D4: 3 | E4: WH3 | F4: WH3-L04 | G4: WH2 | H4: WH2-L05 | I4: Open
A5: TR0004 | B5: 46039 | C5: ITEM008 | D5: 1 | E5: WH2 | F5: WH2-L03 | G5: WH3 | H5: WH3-L03 | I5: Open
A6: TR0005 | B6: 46040 | C6: ITEM025 | D6: 2 | E6: WH1 | F6: WH1-L01 | G6: WH2 | H6: WH2-L05 | I6: Transferred
A7: TR0006 | B7: 46041 | C7: ITEM025 | D7: 10 | E7: WH1 | F7: WH1-L03 | G7: WH2 | H7: WH2-L05 | I7: Open
A8: TR0007 | B8: 46042 | C8: ITEM008 | D8: 3 | E8: WH2 | F8: WH2-L02 | G8: WH1 | H8: WH1-L03 | I8: Transferred
A9: TR0008 | B9: 46043 | C9: ITEM009 | D9: 1 | E9: WH2 | F9: WH2-L05 | G9: WH1 | H9: WH1-L02 | I9: Transferred
A10: TR0009 | B10: 46044 | C10: ITEM004 | D10: 1 | E10: WH3 | F10: WH3-L02 | G10: WH2 | H10: WH2-L04 | I10: Open
A11: TR0010 | B11: 46045 | C11: ITEM011 | D11: 2 | E11: WH2 | F11: WH2-L04 | G11: WH3 | H11: WH3-L04 | I11: Transferred
A12: TR0011 | B12: 46046 | C12: ITEM013 | D12: 5 | E12: WH2 | F12: WH2-L01 | G12: WH3 | H12: WH3-L01 | I12: Transferred
A13: TR0012 | B13: 46047 | C13: ITEM019 | D13: 3 | E13: WH3 | F13: WH3-L02 | G13: WH1 | H13: WH1-L02 | I13: Transferred
... A26: TR0025 | B26: 46060 | C26: ITEM001 | D26: 3 | E26: WH1 | F26: WH1-L05 | G26: WH3 | H26: WH3-L05 | I26: Open

Sheet GLJournals
A1: JournalId | B1: JournalDate | C1: Account | D1: Description | E1: Debit | F1: Credit | G1: Dimension | H1: Status
A2: GL0001 | B2: 46028 | C2: 610100 | D2: Office Expense | E2: 0 | F2: 100 | G2: CostCtr-10 | H2: Posted
A3: GL0002 | B3: 46029 | C3: 400100 | D3: Product Revenue | E3: 0 | F3: 100 | G3: CostCtr-10 | H3: Posted
A4: GL0003 | B4: 46030 | C4: 120100 | D4: Accounts Receivable | E4: 0 | F4: 750 | G4: CostCtr-10 | H4: Posted
A5: GL0004 | B5: 46031 | C5: 500100 | D5: Cost of Goods Sold | E5: 350 | F5: 0 | G5: Dept-200 | H5: Posted
A6: GL0005 | B6: 46032 | C6: 500100 | D6: Cost of Goods Sold | E6: 0 | F6: 500 | G6: Dept-300 | H6: Posted
A7: GL0006 | B7: 46033 | C7: 130100 | D7: Inventory | E7: 1000 | F7: 0 | G7: CostCtr-10 | H7: Posted
A8: GL0007 | B8: 46034 | C8: 120100 | D8: Accounts Receivable | E8: 0 | F8: 350 | G8: Dept-300 | H8: Posted
A9: GL0008 | B9: 46035 | C9: 120100 | D9: Accounts Receivable | E9: 500 | F9: 0 | G9: CostCtr-10 | H9: Posted
A10: GL0009 | B10: 46036 | C10: 130100 | D10: Inventory | E10: 50 | F10: 0 | G10: Dept-300 | H10: Posted
A11: GL0010 | B11: 46037 | C11: 220100 | D11: Sales Tax Payable | E11: 750 | F11: 0 | G11: Dept-200 | H11: Posted
A12: GL0011 | B12: 46038 | C12: 400100 | D12: Product Revenue | E12: 1000 | F12: 0 | G12: Dept-300 | H12: Posted
A13: GL0012 | B13: 46039 | C13: 220100 | D13: Sales Tax Payable | E13: 750 | F13: 0 | G13: Dept-100 | H13: Posted
... A31: GL0030 | B31: 46057 | C31: 130100 | D31: Inventory | E31: 0 | F31: 75 | G31: CostCtr-10 | H31: Posted

Sheet Payments
A1: PaymentId | B1: PaymentDate | C1: PartyType | D1: PartyId | E1: ReferenceId | F1: PaymentMethod | G1: Amount | H1: Currency | I1: Status
A2: PAYV001 | B2: 46066 | C2: Vendor | D2: VEND011 | E2: PO0001 | F2: Check | G2: =PurchaseOrders!G2 -> 200 | H2: USD | I2: Posted
A3: PAYV002 | B3: 46067 | C3: Vendor | D3: VEND004 | E3: PO0002 | F3: Wire | G3: =PurchaseOrders!G3 -> 10000 | H3: USD | I3: Posted
A4: PAYV003 | B4: 46068 | C4: Vendor | D4: VEND011 | E4: PO0003 | F4: Wire | G4: =PurchaseOrders!G4 -> 750 | H4: USD | I4: Posted
A5: PAYV004 | B5: 46069 | C5: Vendor | D5: VEND014 | E5: PO0004 | F5: Check | G5: =PurchaseOrders!G5 -> 3600 | H5: USD | I5: Posted
A6: PAYV005 | B6: 46070 | C6: Vendor | D6: VEND001 | E6: PO0005 | F6: Wire | G6: =PurchaseOrders!G6 -> 540 | H6: USD | I6: Posted
A7: PAYV006 | B7: 46071 | C7: Vendor | D7: VEND004 | E7: PO0006 | F7: EFT | G7: =PurchaseOrders!G7 -> 2000 | H7: USD | I7: Posted
A8: PAYV007 | B8: 46072 | C8: Vendor | D8: VEND003 | E8: PO0007 | F8: Wire | G8: =PurchaseOrders!G8 -> 7500 | H8: USD | I8: Posted
A9: PAYV008 | B9: 46073 | C9: Vendor | D9: VEND013 | E9: PO0008 | F9: EFT | G9: =PurchaseOrders!G9 -> 2400 | H9: USD | I9: Posted
A10: PAYV009 | B10: 46074 | C10: Vendor | D10: VEND002 | E10: PO0009 | F10: EFT | G10: =PurchaseOrders!G10 -> 360 | H10: USD | I10: Posted
A11: PAYV010 | B11: 46075 | C11: Vendor | D11: VEND004 | E11: PO0010 | F11: Wire | G11: =PurchaseOrders!G11 -> 10000 | H11: USD | I11: Posted
A12: PAYC001 | B12: 46081 | C12: Customer | D12: CUST007 | E12: SO0001 | F12: Wire | G12: =SalesOrders!G2 -> 163.5 | H12: USD | I12: Posted
A13: PAYC002 | B13: 46082 | C13: Customer | D13: CUST017 | E13: SO0002 | F13: Card | G13: =SalesOrders!G3 -> 276.49 | H13: USD | I13: Posted
A14: PAYC003 | B14: 46083 | C14: Customer | D14: CUST007 | E14: SO0003 | F14: ACH | G14: =SalesOrders!G4 -> 458.7 | H14: USD | I14: Posted
A15: PAYC004 | B15: 46084 | C15: Customer | D15: CUST020 | E15: SO0004 | F15: Wire | G15: =SalesOrders!G5 -> 236.31 | H15: USD | I15: Posted
A16: PAYC005 | B16: 46085 | C16: Customer | D16: CUST017 | E16: SO0005 | F16: ACH | G16: =SalesOrders!G6 -> 229.35 | H16: USD | I16: Posted
A17: PAYC006 | B17: 46086 | C17: Customer | D17: CUST010 | E17: SO0006 | F17: Card | G17: =SalesOrders!G7 -> 389.56 | H17: USD | I17: Posted
A18: PAYC007 | B18: 46087 | C18: Customer | D18: CUST013 | E18: SO0007 | F18: ACH | G18: =SalesOrders!G8 -> 1658.94 | H18: USD | I18: Posted
A19: PAYC008 | B19: 46088 | C19: Customer | D19: CUST010 | E19: SO0008 | F19: Wire | G19: =SalesOrders!G9 -> 2631 | H19: USD | I19: Posted
A20: PAYC009 | B20: 46089 | C20: Customer | D20: CUST007 | E20: SO0009 | F20: Wire | G20: =SalesOrders!G10 -> 101.28 | H20: USD | I20: Posted
A21: PAYC010 | B21: 46090 | C21: Customer | D21: CUST015 | E21: SO0010 | F21: ACH | G21: =SalesOrders!G11 -> 771.15 | H21: USD | I21: Posted

Sheet OrderTracking
A1: TrackId | B1: SourceType | C1: SourceId | D1: CustomerOrVendor | E1: ItemId | F1: CurrentStatus | G1: CreatedDate | H1: LastUpdated | I1: Owner | J1: Priority | K1: NextAction
A2: TRK0001 | B2: Purchase | C2: PO0001 | D2: VEND008 | E2: ITEM006 | F2: Processed | G2: 46026 | H2: 46027 | I2: Analyst A | J2: Medium | K2: Validate data
A3: TRK0002 | B3: Sales | C3: SO0002 | D3: CUST010 | E3: ITEM012 | F3: Processed | G3: 46027 | H3: 46034 | I3: Analyst B | J3: Low | K3: Close ticket
A4: TRK0003 | B4: Purchase | C4: PO0003 | D4: VEND007 | E4: ITEM019 | F4: In Review | G4: 46028 | H4: 46031 | I4: Analyst B | J4: Low | K4: Close ticket
A5: TRK0004 | B5: Sales | C5: SO0004 | D5: CUST013 | E5: ITEM020 | F5: In Review | G5: 46029 | H5: 46037 | I5: Lead E | J5: Low | K5: Post invoice
A6: TRK0005 | B6: Purchase | C6: PO0005 | D6: VEND008 | E6: ITEM021 | F6: Processed | G6: 46030 | H6: 46038 | I6: Consultant C | J6: High | K6: Validate data
A7: TRK0006 | B7: Sales | C7: SO0006 | D7: CUST015 | E7: ITEM010 | F7: Completed | G7: 46031 | H7: 46034 | I7: Analyst A | J7: Medium | K7: Confirm shipment
A8: TRK0007 | B8: Purchase | C8: PO0007 | D8: VEND010 | E8: ITEM010 | F8: Error | G8: 46032 | H8: 46037 | I8: Support D | J8: Medium | K8: Post invoice
A9: TRK0008 | B9: Sales | C9: SO0008 | D9: CUST013 | E9: ITEM016 | F9: Pending | G9: 46033 | H9: 46037 | I9: Support D | J9: High | K9: Confirm shipment
A10: TRK0009 | B10: Purchase | C10: PO0009 | D10: VEND010 | E10: ITEM010 | F10: Processed | G10: 46034 | H10: 46035 | I10: Support D | J10: Medium | K10: Validate data
A11: TRK0010 | B11: Sales | C11: SO0010 | D11: CUST019 | E11: ITEM022 | F11: Pending | G11: 46035 | H11: 46043 | I11: Consultant C | J11: Low | K11: Close ticket
A12: TRK0011 | B12: Purchase | C12: PO0011 | D12: VEND013 | E12: ITEM012 | F12: In Review | G12: 46036 | H12: 46040 | I12: Lead E | J12: Medium | K12: Post invoice
A13: TRK0012 | B13: Sales | C13: SO0012 | D13: CUST004 | E13: ITEM021 | F13: Pending | G13: 46037 | H13: 46042 | I13: Support D | J13: Low | K13: Close ticket
... A31: TRK0030 | B31: Sales | C31: SO0030 | D31: CUST011 | E31: ITEM025 | F31: In Review | G31: 46055 | H31: 46056 | I31: Consultant C | J31: Low | K31: Post invoice

Sheet Scenarios
A1: ScenarioId | B1: Area | C1: Title | D1: Objective | E1: KeySheets | F1: SuggestedTask
A2: SCN001 | B2: SCM | C2: Procure-to-Pay cycle | D2: Create PO, receive goods, invoice vendor | E2: Vendors, Products, PurchaseOrders | F2: Post one open PO end-to-end
A3: SCN002 | B3: SCM | C3: Order-to-Cash cycle | D3: Create SO, ship, invoice customer | E3: Customers, Products, SalesOrders | F3: Complete one open SO
A4: SCN003 | B4: Technical | C4: Custom order tracking | D4: Extend order tracking and add status logic | E4: OrderTracking | F4: Add field and status validation
A5: SCN004 | B5: Technical | C5: Batch processing | D5: Auto-update pending tracked records | E5: OrderTracking | F5: Create batch job for pending records
A6: SCN005 | B6: Integration | C6: Import purchase lines | D6: Use PO sheet for entity import | E6: PurchaseOrders | F6: Import selected PO rows
A7: SCN006 | B7: Integration | C7: Import sales lines | D7: Use SO sheet for entity import | E7: SalesOrders | F7: Import selected SO rows
A8: SCN007 | B8: Finance | C8: Post expense journal | D8: Use GL journal lines | E8: GLJournals | F8: Post one journal batch
A9: SCN008 | B9: Finance | C9: Receive customer payment | D9: Apply receipt to open invoice | E9: Payments, SalesOrders | F9: Post one customer payment
A10: SCN009 | B10: Finance | C10: Vendor settlement | D10: Apply payment to vendor invoice | E10: Payments, PurchaseOrders | F10: Post one vendor payment
A11: SCN010 | B11: SCM | C11: Inventory transfer | D11: Move stock across warehouses | E11: InventoryTransfers | F11: Post one open transfer
A12: SCN011 | B12: Finance | C12: Reconciliation | D12: Compare invoice vs payment values | E12: Payments, PurchaseOrders, SalesOrders | F12: Investigate mismatches
... A16: SCN015 | B16: Technical | C16: Troubleshooting | D16: Find and resolve failed statuses | E16: OrderTracking | F16: Work all Error rows to completion
